frictionless_ckan_mapper/VERSION
frictionless_ckan_mapper/__init__.py
frictionless_ckan_mapper/ckan_to_frictionless.py
frictionless_ckan_mapper/frictionless_to_ckan.py
frictionless_ckan_mapper-1.0.9.dist-info/LICENSE.md
frictionless_ckan_mapper-1.0.9.dist-info/METADATA
frictionless_ckan_mapper-1.0.9.dist-info/WHEEL
frictionless_ckan_mapper-1.0.9.dist-info/top_level.txt
frictionless_ckan_mapper-1.0.9.dist-info/RECORD
