Metadata-Version: 2.1
Name: frictionless-ckan-mapper
Version: 1.0.9
Summary: A library for mapping CKAN metadata <=> Frictionless metadata.
Home-page: https://github.com/frictionlessdata/frictionless-ckan-mapper
Author: Open Knowledge International
License: MIT
Keywords: data,ckan,frictionless,conversion,package,dataset,resource
Platform: UNKNOWN
Classifier: Environment :: Web Environment
Classifier: Intended Audience :: Developers
Classifier: License :: OSI Approved :: MIT License
Classifier: Operating System :: OS Independent
Classifier: Programming Language :: Python :: 3.6
Classifier: Programming Language :: Python :: 2.7
Classifier: Topic :: Internet :: WWW/HTTP :: Dynamic Content
Classifier: Topic :: Software Development :: Libraries :: Python Modules
Requires-Dist: six (<2.0,>=1.9)
Requires-Dist: unidecode
Provides-Extra: develop
Requires-Dist: pylama ; extra == 'develop'
Requires-Dist: tox ; extra == 'develop'
